clevr/__init__.py
clevr/helpers.py
clevr/library_helpers.py
clevr/api_resources/__init__.py
clevr/api_resources/athena.py
clevr/api_resources/layers.py
clevr/api_resources/persona.py
clevr/api_resources/platform.py
clevr-0.5.14.dist-info/METADATA
clevr-0.5.14.dist-info/WHEEL
clevr-0.5.14.dist-info/top_level.txt
clevr-0.5.14.dist-info/RECORD
